shared_utils/__init__.py
shared_utils/file_utils.py
shared_utils/gcs_helper.py
shared_utils/helper.py
shared_utils/job_monitor.py
shared_utils/journal_helper.py
shared_utils/mailer.py
shared_utils/mailer_helper.py
shared_utils/metrics_helper.py
shared_utils/netsuite_helper.py
shared_utils/netsuite_journal_entry.py
shared_utils/utils.py
ra_netsuite_shared_utils-0.7.0.dist-info/METADATA
ra_netsuite_shared_utils-0.7.0.dist-info/WHEEL
ra_netsuite_shared_utils-0.7.0.dist-info/top_level.txt
ra_netsuite_shared_utils-0.7.0.dist-info/RECORD
