Metadata-Version: 2.4
Name: ra_netsuite_shared_utils
Version: 0.7.0
Author: Vrishabh Agamya
Requires-Dist: requests
Requires-Dist: requests-oauthlib
Requires-Dist: google-cloud-storage
Requires-Dist: google-cloud-pubsub
Requires-Dist: google-cloud-tasks
Dynamic: author
Dynamic: requires-dist
